bannercli/__init__.py
bannercli/bannercli.py
bannercli/cli.py
bannercli-0.1.0.dist-info/AUTHORS.rst
bannercli-0.1.0.dist-info/LICENSE
bannercli-0.1.0.dist-info/METADATA
bannercli-0.1.0.dist-info/WHEEL
bannercli-0.1.0.dist-info/entry_points.txt
bannercli-0.1.0.dist-info/top_level.txt
bannercli-0.1.0.dist-info/RECORD
