Metadata-Version: 2.1
Name: bannercli
Version: 0.1.0
Summary: Fancy Text on Terminal.
Home-page: https://github.com/insumanth/bannercli
Author: Sumanth
Author-email: sumanthreddystar@gmail.com
License: GNU General Public License v3
Keywords: bannercli
Platform: UNKNOWN
Classifier: Development Status :: 2 - Pre-Alpha
Classifier: Intended Audience :: Developers
Classifier: License :: OSI Approved :: GNU General Public License v3 (GPLv3)
Classifier: Natural Language :: English
Classifier: Programming Language :: Python :: 3
Classifier: Programming Language :: Python :: 3.6
Classifier: Programming Language :: Python :: 3.7
Classifier: Programming Language :: Python :: 3.8
Requires-Python: >=3.6
License-File: LICENSE
License-File: AUTHORS.rst
